portal_visualization/__init__.py
portal_visualization/assays.py
portal_visualization/builder_factory.py
portal_visualization/cli.py
portal_visualization/client.py
portal_visualization/constants.py
portal_visualization/defaults.json
portal_visualization/epic_factory.py
portal_visualization/mock_client.py
portal_visualization/paths.py
portal_visualization/utils.py
portal_visualization/builders/__init__.py
portal_visualization/builders/anndata_builders.py
portal_visualization/builders/base_builders.py
portal_visualization/builders/epic_builders.py
portal_visualization/builders/imaging_builders.py
portal_visualization/builders/object_by_analyte_builders.py
portal_visualization/builders/scatterplot_builders.py
portal_visualization/builders/sprm_builders.py
portal_visualization-0.4.22.dist-info/licenses/LICENSE
portal_visualization-0.4.22.dist-info/METADATA
portal_visualization-0.4.22.dist-info/WHEEL
portal_visualization-0.4.22.dist-info/entry_points.txt
portal_visualization-0.4.22.dist-info/top_level.txt
portal_visualization-0.4.22.dist-info/RECORD
