Metadata-Version: 2.4
Name: portal-visualization
Version: 0.4.22
Summary: Given HuBMAP Dataset JSON, creates a Vitessce configuration.
Author-email: Chuck McCallum <mccallucc@gmail.com>
Maintainer-email: HIDIVE Lab at Harvard Medical School <hidive@hms.harvard.edu>, Nikolay Akhmetov <nikolay_akhmetov@hms.harvard.edu>, Tabassum Kakar <tabassum_kakar@hms.harvard.edu>, John Conroy <john_conroy@hms.harvard.edu>, Lisa Choy <lisa_choy@hms.harvard.edu>
License: MIT
Project-URL: Homepage, https://github.com/hubmapconsortium/portal-visualization
Project-URL: Bug Tracker, https://github.com/hubmapconsortium/portal-visualization/issues
Project-URL: Source Code, https://github.com/hubmapconsortium/portal-visualization
Project-URL: Documentation, https://github.com/hubmapconsortium/portal-visualization#readme
Project-URL: Changelog, https://github.com/hubmapconsortium/portal-visualization/releases
Keywords: hubmap,vitessce,visualization,bioinformatics,imaging,sequencing,single-cell,spatial-transcriptomics
Classifier: Development Status :: 4 - Beta
Classifier: Intended Audience :: Science/Research
Classifier: Intended Audience :: Developers
Classifier: License :: OSI Approved :: MIT License
Classifier: Operating System :: OS Independent
Classifier: Programming Language :: Python :: 3
Classifier: Programming Language :: Python :: 3.10
Classifier: Programming Language :: Python :: 3.11
Classifier: Programming Language :: Python :: 3.12
Classifier: Programming Language :: Python :: 3.13
Classifier: Programming Language :: Python :: 3 :: Only
Classifier: Topic :: Scientific/Engineering :: Bio-Informatics
Classifier: Topic :: Scientific/Engineering :: Visualization
Classifier: Topic :: Software Development :: Libraries :: Python Modules
Requires-Python: >=3.10
License-File: LICENSE
Provides-Extra: full
Requires-Dist: vitessce==3.7.4; extra == "full"
Requires-Dist: hubmap-commons>=2.0.15; extra == "full"
Requires-Dist: flask>=2.0.0; extra == "full"
Requires-Dist: werkzeug>=2.0.0; extra == "full"
Requires-Dist: requests>=2.27.1; extra == "full"
Requires-Dist: nbformat>=5.1.3; extra == "full"
Requires-Dist: zarr>=2.17.2; extra == "full"
Requires-Dist: aiohttp>=3.8.1; extra == "full"
Requires-Dist: fsspec>=2022.1.0; extra == "full"
Requires-Dist: python-datauri>=2.2.0; extra == "full"
Provides-Extra: dev
Requires-Dist: pytest>=7.0.0; extra == "dev"
Requires-Dist: pytest-mock>=3.7.0; extra == "dev"
Requires-Dist: coverage>=7.6.4; extra == "dev"
Requires-Dist: pyyaml>=6.0.2; extra == "dev"
Requires-Dist: ruff>=0.8.0; extra == "dev"
Requires-Dist: build>=0.10.0; extra == "dev"
Provides-Extra: all
Requires-Dist: portal-visualization[dev,full]; extra == "all"
Dynamic: license-file
